discord_user_bot/__init__.py
discord_user_bot-0.0.2.dist-info/METADATA
discord_user_bot-0.0.2.dist-info/WHEEL
discord_user_bot-0.0.2.dist-info/top_level.txt
discord_user_bot-0.0.2.dist-info/RECORD
